app/AddressBook.bin
app/NoteBook.bin
app/adressbook.py
app/cleanfolder.py
app/file_parser.py
app/main.py
app/normalize.py
app/notebook.py
venv/bin/activate_this.py
venv/bin/rst2html.py
venv/bin/rst2html4.py
venv/bin/rst2html5.py
venv/bin/rst2latex.py
venv/bin/rst2man.py
venv/bin/rst2odt.py
venv/bin/rst2odt_prepstyles.py
venv/bin/rst2pseudoxml.py
venv/bin/rst2s5.py
venv/bin/rst2xetex.py
venv/bin/rst2xml.py
venv/bin/rstpep2html.py
helpme_assistance-0.2.9.dist-info/LICENSE
helpme_assistance-0.2.9.dist-info/METADATA
helpme_assistance-0.2.9.dist-info/WHEEL
helpme_assistance-0.2.9.dist-info/entry_points.txt
helpme_assistance-0.2.9.dist-info/top_level.txt
helpme_assistance-0.2.9.dist-info/RECORD
