Metadata-Version: 2.1
Name: helpme-assistance
Version: 0.2.9
Summary: The project 'HelpMe' - its your personal CLI assistant. AddressBook, NoteBook, CleanFolder - in one app.
Home-page: https://github.com/vlad-bb/HelpMe-project
Author: ITeams
Author-email: vlad_bb@icloud.com, nataliia.kovalchuk90@gmail.com, saifulianna.it@gmail.com
Classifier: Programming Language :: Python :: 3
Classifier: License :: OSI Approved :: MIT License
Classifier: Operating System :: OS Independent
License-File: LICENSE
Requires-Dist: phonenumbers (==8.12.50)
